lm/__init__.py
lm/cli.py
lm/lm.py
lm-0.1.0.dist-info/AUTHORS.rst
lm-0.1.0.dist-info/LICENSE
lm-0.1.0.dist-info/METADATA
lm-0.1.0.dist-info/WHEEL
lm-0.1.0.dist-info/entry_points.txt
lm-0.1.0.dist-info/top_level.txt
lm-0.1.0.dist-info/RECORD
