Metadata-Version: 2.1
Name: lm
Version: 0.1.0
Summary: End to End Language Model Pipeline built for training speed
Home-page: https://github.com/Mistobaan/lm
Author: Fabrizio Milo
Author-email: fmilo@entropysource.com
License: Apache Software License 2.0
Keywords: lm
Platform: UNKNOWN
Classifier: Development Status :: 2 - Pre-Alpha
Classifier: Intended Audience :: Developers
Classifier: License :: OSI Approved :: Apache Software License
Classifier: Natural Language :: English
Classifier: Programming Language :: Python :: 3
Classifier: Programming Language :: Python :: 3.5
Classifier: Programming Language :: Python :: 3.6
Classifier: Programming Language :: Python :: 3.7
Classifier: Programming Language :: Python :: 3.8
Requires-Python: >=3.7
